FormatRosterData/FormatData.py
FormatRosterData/Main.py
FormatRosterData/Misc.py
FormatRosterData/SportCatagory.py
FormatRosterData/WebsiteScraping.py
FormatRosterData/_Logger.py
FormatRosterData/_Reporter.py
FormatRosterData/__init__.py
FormatRosterData-1.0.13.dist-info/METADATA
FormatRosterData-1.0.13.dist-info/RECORD
FormatRosterData-1.0.13.dist-info/WHEEL
FormatRosterData-1.0.13.dist-info/top_level.txt
