Metadata-Version: 2.1
Name: FormatRosterData
Version: 1.0.13
Summary: UNKNOWN
Home-page: UNKNOWN
Author: Troy1010
License: UNKNOWN
Platform: UNKNOWN
Requires-Python: >=3.6
Requires-Dist: TM-CommonPy
Requires-Dist: nose
Requires-Dist: openpyxl
Requires-Dist: requests
Requires-Dist: lxml
